Data_mem_tb/data_mem.sv
module data_mem #(

    parameter ADDRESS_WIDTH = 8, //it will come as 32 bits but we will only take the first 8
              DATA_WIDTH = 8 // this used to be 32
   
)(

    input  logic clk,   //only for Writing to Data Memory 
    input  logic   WE,   // Write Enable flag
    input  logic [DATA_WIDTH-1:0] WD,  //The Data we recieve from the rs2
    input  logic [DATA_WIDTH-1:0] A,   // The Adress that comes from ALU Result irrespective we are loading or stroring
    output logic [DATA_WIDTH-1:0] RD // Data read from the memory
);   


logic [DATA_WIDTH-1:0] data_memory [2**ADDRESS_WIDTH-1:0];

initial begin
    $display("Loading ram...");
    $readmemh("ram_array.mem", data_memory); 
end;




always_ff @(posedge clk) begin
    if (WE) 
        data_memory[A] <= WD; // we are storing word 
end

assign RD = data_memory[A]; // we are loading word 

endmodule

Data_mem_tb/data_mem.vcd
$version Generated by VerilatedVcd $end
$date Tue Nov 28 15:08:23 2023 $end
$timescale 1ps $end

 $scope module TOP $end
  $var wire  8 & A [7:0] $end
  $var wire  8 ' RD [7:0] $end
  $var wire  8 % WD [7:0] $end
  $var wire  1 $ WE $end
  $var wire  1 # clk $end
  $scope module data_mem $end
   $var wire  8 & A [7:0] $end
   $var wire 32 ( ADDRESS_WIDTH [31:0] $end
   $var wire 32 ( DATA_WIDTH [31:0] $end
   $var wire  8 ' RD [7:0] $end
   $var wire  8 % WD [7:0] $end
   $var wire  1 $ WE $end
   $var wire  1 # clk $end
  $upscope $end
 $upscope $end
$enddefinitions $end


#0
0#
0$
b00000000 %
b00000000 &
b00000000 '
b00000000000000000000000000001000 (
#1
1#
b11111110 '
#2
0#
#3
1#
#4
0#
b00000100 &
#5
1#
b11111101 '
#6
0#
b00001000 &
#7
1#
b11111011 '
#8
0#
b00001100 &
#9
1#
b11111000 '
#10
0#
b00010000 &
#11
1#
b11110100 '
#12
0#
b00010100 &
#13
1#
b11101111 '
#14
0#
b00011000 &
#15
1#
b11101000 '
#16
0#
b00011100 &
#17
1#
b11100001 '
#18
0#
b00100000 &
#19
1#
b11011000 '
#20
0#
b00100100 &
#21
1#
b11001111 '
#22
0#
b00101000 &
#23
1#
b11000101 '
#24
0#
b00101100 &
#25
1#
b10111010 '
#26
0#
b00110000 &
#27
1#
b10101111 '
#28
0#
b00110100 &
#29
1#
b10100011 '
#30
0#
b00111000 &
#31
1#
b10010111 '
#32
0#
b00111100 &
#33
1#
b10001011 '
#34
0#
b01000000 &
#35
1#
b01111110 '
#36
0#
b01000100 &
#37
1#
b01110010 '
#38
0#
b01001000 &
#39
1#
b01100110 '
#40
0#
b01001100 &
#41
1#
b01011010 '
#42
0#
b01010000 &
#43
1#
b01001110 '
#44
0#
b01010100 &
#45
1#
b01000011 '
#46
0#
b01011000 &
#47
1#
b00111000 '
#48
0#
b01011100 &
#49
1#
b00101110 '
#50
0#
b01100000 &
#51
1#
b00100101 '
#52
0#
b01100100 &
#53
1#
b00011100 '
#54
0#
b01101000 &
#55
1#
b00010101 '
#56
0#
b01101100 &
#57
1#
b00001110 '
#58
0#
b01110000 &
#59
1#
b00001001 '
#60
0#
b01110100 &
#61
1#
b00000101 '
#62
0#
b01111000 &
#63
1#
b00000010 '
#64
0#
b01111100 &
#65
1#
b00000000 '
#66
0#
b10000000 &
#67
1#
#68
0#
b10000100 &
#69
1#
#70
0#
b10001000 &
#71
1#
b00000010 '
#72
0#
b10001100 &
#73
1#
b00000101 '
#74
0#
b10010000 &
#75
1#
b00001001 '
#76
0#
b10010100 &
#77
1#
b00001110 '
#78
0#
b10011000 &
#79
1#
b00010101 '
#80
0#
b10011100 &
#81
1#
b00011100 '
#82
0#
b10100000 &
#83
1#
b00100101 '
#84
0#
b10100100 &
#85
1#
b00101110 '
#86
0#
b10101000 &
#87
1#
b00111000 '
#88
0#
b10101100 &
#89
1#
b01000011 '
#90
0#
b10110000 &
#91
1#
b01001110 '
#92
0#
b10110100 &
#93
1#
b01011010 '
#94
0#
b10111000 &
#95
1#
b01100110 '
#96
0#
b10111100 &
#97
1#
b01110010 '
#98
0#
b11000000 &
#99
1#
b01111111 '
#100
0#
b11000100 &
#101
1#
b10001011 '
#102
0#
b11001000 &
#103
1#
b10010111 '
#104
0#
b11001100 &
#105
1#
b10100011 '
#106
0#
b11010000 &
#107
1#
b10101111 '
#108
0#
b11010100 &
#109
1#
b10111010 '
#110
0#
b11011000 &
#111
1#
b11000101 '
#112
0#
b11011100 &
#113
1#
b11001111 '
#114
0#
b11100000 &
#115
1#
b11011000 '
#116
0#
b11100100 &
#117
1#
b11100001 '
#118
0#
b11101000 &
#119
1#
b11101000 '
#120
0#
b11101100 &
#121
1#
b11101111 '
#122
0#
b11110000 &
#123
1#
b11110100 '
#124
0#
b11110100 &
#125
1#
b11111000 '
#126
0#
b11111000 &
#127
1#
b11111011 '
#128
0#
b11111100 &
#129
1#
b11111101 '
#130
0#
b00000000 &
#131
1#
b11111110 '
#132
0#
b00000100 &
#133
1#
b11111101 '
#134
0#
b00001000 &
#135
1#
b11111011 '
#136
0#
b00001100 &
#137
1#
b11111000 '
#138
0#
b00010000 &
#139
1#
b11110100 '
#140
0#
b00010100 &
#141
1#
b11101111 '
#142
0#
b00011000 &
#143
1#
b11101000 '
#144
0#
b00011100 &
#145
1#
b11100001 '
#146
0#
b00100000 &
#147
1#
b11011000 '
#148
0#
b00100100 &
#149
1#
b11001111 '
#150
0#
b00101000 &
#151
1#
b11000101 '
#152
0#
b00101100 &
#153
1#
b10111010 '
#154
0#
b00110000 &
#155
1#
b10101111 '
#156
0#
b00110100 &
#157
1#
b10100011 '
#158
0#
b00111000 &
#159
1#
b10010111 '
#160
0#
b00111100 &
#161
1#
b10001011 '
#162
0#
b01000000 &
#163
1#
b01111110 '
#164
0#
b01000100 &
#165
1#
b01110010 '
#166
0#
b01001000 &
#167
1#
b01100110 '
#168
0#
b01001100 &
#169
1#
b01011010 '
#170
0#
b01010000 &
#171
1#
b01001110 '
#172
0#
b01010100 &
#173
1#
b01000011 '
#174
0#
b01011000 &
#175
1#
b00111000 '
#176
0#
b01011100 &
#177
1#
b00101110 '
#178
0#
b01100000 &
#179
1#
b00100101 '
#180
0#
b01100100 &
#181
1#
b00011100 '
#182
0#
b01101000 &
#183
1#
b00010101 '
#184
0#
b01101100 &
#185
1#
b00001110 '
#186
0#
b01110000 &
#187
1#
b00001001 '
#188
0#
b01110100 &
#189
1#
b00000101 '
#190
0#
b01111000 &
#191
1#
b00000010 '
#192
0#
b01111100 &
#193
1#
b00000000 '
#194
0#
b10000000 &
#195
1#
#196
0#
b10000100 &
#197
1#
#198
0#
b10001000 &
#199
1#
b00000010 '
#200
0#
b10001100 &
#201
1#
b00000101 '
#202
0#
b10010000 &
#203
1#
b00001001 '
#204
0#
b10010100 &
#205
1#
b00001110 '
#206
0#
b10011000 &
#207
1#
b00010101 '
#208
0#
b10011100 &
#209
1#
b00011100 '
#210
0#
b10100000 &
#211
1#
b00100101 '
#212
0#
b10100100 &
#213
1#
b00101110 '
#214
0#
b10101000 &
#215
1#
b00111000 '
#216
0#
b10101100 &
#217
1#
b01000011 '
#218
0#
b10110000 &
#219
1#
b01001110 '
#220
0#
b10110100 &
#221
1#
b01011010 '
#222
0#
b10111000 &
#223
1#
b01100110 '
#224
0#
b10111100 &
#225
1#
b01110010 '
#226
0#
b11000000 &
#227
1#
b01111111 '
#228
0#
b11000100 &
#229
1#
b10001011 '
#230
0#
b11001000 &
#231
1#
b10010111 '
#232
0#
b11001100 &
#233
1#
b10100011 '
#234
0#
b11010000 &
#235
1#
b10101111 '
#236
0#
b11010100 &
#237
1#
b10111010 '
#238
0#
b11011000 &
#239
1#
b11000101 '
#240
0#
b11011100 &
#241
1#
b11001111 '
#242
0#
b11100000 &
#243
1#
b11011000 '
#244
0#
b11100100 &
#245
1#
b11100001 '
#246
0#
b11101000 &
#247
1#
b11101000 '
#248
0#
b11101100 &
#249
1#
b11101111 '
#250
0#
b11110000 &
#251
1#
b11110100 '
#252
0#
b11110100 &
#253
1#
b11111000 '
#254
0#
b11111000 &
#255
1#
b11111011 '
#256
0#
b11111100 &
#257
1#
b11111101 '
#258
0#
b00000000 &
#259
1#
b11111110 '
#260
0#
b00000100 &
#261
1#
b11111101 '
#262
0#
b00001000 &
#263
1#
b11111011 '
#264
0#
b00001100 &
#265
1#
b11111000 '
#266
0#
b00010000 &
#267
1#
b11110100 '
#268
0#
b00010100 &
#269
1#
b11101111 '
#270
0#
b00011000 &
#271
1#
b11101000 '
#272
0#
b00011100 &
#273
1#
b11100001 '
#274
0#
b00100000 &
#275
1#
b11011000 '
#276
0#
b00100100 &
#277
1#
b11001111 '
#278
0#
b00101000 &
#279
1#
b11000101 '
#280
0#
b00101100 &
#281
1#
b10111010 '
#282
0#
b00110000 &
#283
1#
b10101111 '
#284
0#
b00110100 &
#285
1#
b10100011 '
#286
0#
b00111000 &
#287
1#
b10010111 '
#288
0#
b00111100 &
#289
1#
b10001011 '
#290
0#
b01000000 &
#291
1#
b01111110 '
#292
0#
b01000100 &
#293
1#
b01110010 '
#294
0#
b01001000 &
#295
1#
b01100110 '
#296
0#
b01001100 &
#297
1#
b01011010 '
#298
0#
b01010000 &
#299
1#
b01001110 '
#300
0#
b01010100 &
#301
1#
b01000011 '
#302
0#
b01011000 &
#303
1#
b00111000 '
#304
0#
b01011100 &
#305
1#
b00101110 '
#306
0#
b01100000 &
#307
1#
b00100101 '
#308
0#
b01100100 &
#309
1#
b00011100 '
#310
0#
b01101000 &
#311
1#
b00010101 '
#312
0#
b01101100 &
#313
1#
b00001110 '
#314
0#
b01110000 &
#315
1#
b00001001 '
#316
0#
b01110100 &
#317
1#
b00000101 '
#318
0#
b01111000 &
#319
1#
b00000010 '
#320
0#
b01111100 &
#321
1#
b00000000 '
#322
0#
b10000000 &
#323
1#
#324
0#
b10000100 &
#325
1#
#326
0#
b10001000 &
#327
1#
b00000010 '
#328
0#
b10001100 &
#329
1#
b00000101 '
#330
0#
b10010000 &
#331
1#
b00001001 '
#332
0#
b10010100 &
#333
1#
b00001110 '
#334
0#
b10011000 &
#335
1#
b00010101 '
#336
0#
b10011100 &
#337
1#
b00011100 '
#338
0#
b10100000 &
#339
1#
b00100101 '
#340
0#
b10100100 &
#341
1#
b00101110 '
#342
0#
b10101000 &
#343
1#
b00111000 '
#344
0#
b10101100 &
#345
1#
b01000011 '
#346
0#
b10110000 &
#347
1#
b01001110 '
#348
0#
b10110100 &
#349
1#
b01011010 '
#350
0#
b10111000 &
#351
1#
b01100110 '
#352
0#
b10111100 &
#353
1#
b01110010 '
#354
0#
b11000000 &
#355
1#
b01111111 '
#356
0#
b11000100 &
#357
1#
b10001011 '
#358
0#
b11001000 &
#359
1#
b10010111 '
#360
0#
b11001100 &
#361
1#
b10100011 '
#362
0#
b11010000 &
#363
1#
b10101111 '
#364
0#
b11010100 &
#365
1#
b10111010 '
#366
0#
b11011000 &
#367
1#
b11000101 '
#368
0#
b11011100 &
#369
1#
b11001111 '
#370
0#
b11100000 &
#371
1#
b11011000 '
#372
0#
b11100100 &
#373
1#
b11100001 '
#374
0#
b11101000 &
#375
1#
b11101000 '
#376
0#
b11101100 &
#377
1#
b11101111 '
#378
0#
b11110000 &
#379
1#
b11110100 '
#380
0#
b11110100 &
#381
1#
b11111000 '
#382
0#
b11111000 &
#383
1#
b11111011 '
#384
0#
b11111100 &
#385
1#
b11111101 '
#386
0#
b00000000 &
#387
1#
b11111110 '
#388
0#
b00000100 &
#389
1#
b11111101 '
#390
0#
b00001000 &
#391
1#
b11111011 '
#392
0#
b00001100 &
#393
1#
b11111000 '
#394
0#
b00010000 &
#395
1#
b11110100 '
#396
0#
b00010100 &
#397
1#
b11101111 '
#398
0#
b00011000 &
#399
1#
b11101000 '
#400
0#
b00011100 &
#401
1#
b11100001 '
#402
0#
b00100000 &
#403
1#
b11011000 '
#404
0#
b00100100 &
#405
1#
b11001111 '
#406
0#
b00101000 &
#407
1#
b11000101 '
#408
0#
b00101100 &
#409
1#
b10111010 '
#410
0#
b00110000 &
#411
1#
b10101111 '
#412
0#
b00110100 &
#413
1#
b10100011 '
#414
0#
b00111000 &
#415
1#
b10010111 '
#416
0#
b00111100 &
#417
1#
b10001011 '
#418
0#
b01000000 &
#419
1#
b01111110 '
#420
0#
b01000100 &
#421
1#
b01110010 '
#422
0#
b01001000 &
#423
1#
b01100110 '
#424
0#
b01001100 &
#425
1#
b01011010 '
#426
0#
b01010000 &
#427
1#
b01001110 '
#428
0#
b01010100 &
#429
1#
b01000011 '
#430
0#
b01011000 &
#431
1#
b00111000 '
#432
0#
b01011100 &
#433
1#
b00101110 '
#434
0#
b01100000 &
#435
1#
b00100101 '
#436
0#
b01100100 &
#437
1#
b00011100 '
#438
0#
b01101000 &
#439
1#
b00010101 '
#440
0#
b01101100 &
#441
1#
b00001110 '
#442
0#
b01110000 &
#443
1#
b00001001 '
#444
0#
b01110100 &
#445
1#
b00000101 '
#446
0#
b01111000 &
#447
1#
b00000010 '
#448
0#
b01111100 &
#449
1#
b00000000 '
#450
0#
b10000000 &
#451
1#
#452
0#
b10000100 &
#453
1#
#454
0#
b10001000 &
#455
1#
b00000010 '
#456
0#
b10001100 &
#457
1#
b00000101 '
#458
0#
b10010000 &
#459
1#
b00001001 '
#460
0#
b10010100 &
#461
1#
b00001110 '
#462
0#
b10011000 &
#463
1#
b00010101 '
#464
0#
b10011100 &
#465
1#
b00011100 '
#466
0#
b10100000 &
#467
1#
b00100101 '
#468
0#
b10100100 &
#469
1#
b00101110 '
#470
0#
b10101000 &
#471
1#
b00111000 '
#472
0#
b10101100 &
#473
1#
b01000011 '
#474
0#
b10110000 &
#475
1#
b01001110 '
#476
0#
b10110100 &
#477
1#
b01011010 '
#478
0#
b10111000 &
#479
1#
b01100110 '
#480
0#
b10111100 &
#481
1#
b01110010 '
#482
0#
b11000000 &
#483
1#
b01111111 '
#484
0#
b11000100 &
#485
1#
b10001011 '
#486
0#
b11001000 &
#487
1#
b10010111 '
#488
0#
b11001100 &
#489
1#
b10100011 '
#490
0#
b11010000 &
#491
1#
b10101111 '
#492
0#
b11010100 &
#493
1#
b10111010 '
#494
0#
b11011000 &
#495
1#
b11000101 '
#496
0#
b11011100 &
#497
1#
b11001111 '
#498
0#
b11100000 &
#499
1#
b11011000 '
#500
0#
b11100100 &
#501
1#
b11100001 '
#502
0#
b11101000 &
#503
1#
b11101000 '
#504
0#
b11101100 &
#505
1#
b11101111 '
#506
0#
b11110000 &
#507
1#
b11110100 '
#508
0#
b11110100 &
#509
1#
b11111000 '
#510
0#
b11111000 &
#511
1#
b11111011 '
#512
0#
b11111100 &
#513
1#
b11111101 '
#514
0#
b00000000 &
#515
1#
b11111110 '
#516
0#
b00000100 &
#517
1#
b11111101 '
#518
0#
b00001000 &
#519
1#
b11111011 '
#520
0#
b00001100 &
#521
1#
b11111000 '
#522
0#
b00010000 &
#523
1#
b11110100 '
#524
0#
b00010100 &
#525
1#
b11101111 '
#526
0#
b00011000 &
#527
1#
b11101000 '
#528
0#
b00011100 &
#529
1#
b11100001 '
#530
0#
b00100000 &
#531
1#
b11011000 '
#532
0#
b00100100 &
#533
1#
b11001111 '
#534
0#
b00101000 &
#535
1#
b11000101 '
#536
0#
b00101100 &
#537
1#
b10111010 '
#538
0#
b00110000 &
#539
1#
b10101111 '
#540
0#
b00110100 &
#541
1#
b10100011 '
#542
0#
b00111000 &
#543
1#
b10010111 '
#544
0#
b00111100 &
#545
1#
b10001011 '
#546
0#
b01000000 &
#547
1#
b01111110 '
#548
0#
b01000100 &
#549
1#
b01110010 '
#550
0#
b01001000 &
#551
1#
b01100110 '
#552
0#
b01001100 &
#553
1#
b01011010 '
#554
0#
b01010000 &
#555
1#
b01001110 '
#556
0#
b01010100 &
#557
1#
b01000011 '
#558
0#
b01011000 &
#559
1#
b00111000 '
#560
0#
b01011100 &
#561
1#
b00101110 '
#562
0#
b01100000 &
#563
1#
b00100101 '
#564
0#
b01100100 &
#565
1#
b00011100 '
#566
0#
b01101000 &
#567
1#
b00010101 '
#568
0#
b01101100 &
#569
1#
b00001110 '
#570
0#
b01110000 &
#571
1#
b00001001 '
#572
0#
b01110100 &
#573
1#
b00000101 '
#574
0#
b01111000 &
#575
1#
b00000010 '
#576
0#
b01111100 &
#577
1#
b00000000 '
#578
0#
b10000000 &
#579
1#
#580
0#
b10000100 &
#581
1#
#582
0#
b10001000 &
#583
1#
b00000010 '
#584
0#
b10001100 &
#585
1#
b00000101 '
#586
0#
b10010000 &
#587
1#
b00001001 '
#588
0#
b10010100 &
#589
1#
b00001110 '
#590
0#
b10011000 &
#591
1#
b00010101 '
#592
0#
b10011100 &
#593
1#
b00011100 '
#594
0#
b10100000 &
#595
1#
b00100101 '
#596
0#
b10100100 &
#597
1#
b00101110 '
#598
0#
b10101000 &
#599
1#
b00111000 '
